dora/__init__.py
dora/__init__.pyi
dora/builder.py
dora/cuda.py
dora/dora.abi3.so
dora/py.typed
dora_rs-0.4.1.dist-info/METADATA
dora_rs-0.4.1.dist-info/WHEEL
dora_rs-0.4.1.dist-info/RECORD
