Metadata-Version: 2.4
Name: dora-rs
Version: 0.4.1
Requires-Dist: pyarrow
Requires-Dist: pyyaml>=6.0
License: MIT
Requires-Python: >=3.7
